proj_flow/__init__.py
proj_flow/__main__.py
proj_flow/dependency.py
proj_flow/api/__init__.py
proj_flow/api/arg.py
proj_flow/api/completers.py
proj_flow/api/ctx.py
proj_flow/api/env.py
proj_flow/api/init.py
proj_flow/api/makefile.py
proj_flow/api/release.py
proj_flow/api/step.py
proj_flow/base/__cmake_version__.py
proj_flow/base/__init__.py
proj_flow/base/cmd.py
proj_flow/base/inspect.py
proj_flow/base/matrix.py
proj_flow/base/name_list.py
proj_flow/base/plugins.py
proj_flow/base/registry.py
proj_flow/base/uname.py
proj_flow/cli/__init__.py
proj_flow/cli/argument.py
proj_flow/cli/finder.py
proj_flow/ext/__init__.py
proj_flow/ext/markdown_changelog.py
proj_flow/ext/re_structured_changelog.py
proj_flow/ext/store.py
proj_flow/ext/cplusplus/__init__.py
proj_flow/ext/cplusplus/cmake/__init__.py
proj_flow/ext/cplusplus/cmake/parser.py
proj_flow/ext/cplusplus/cmake/presets.py
proj_flow/ext/cplusplus/cmake/project.py
proj_flow/ext/cplusplus/cmake/steps.py
proj_flow/ext/cplusplus/conan/__init__.py
proj_flow/ext/cplusplus/conan/_conan.py
proj_flow/ext/github/__init__.py
proj_flow/ext/github/cli.py
proj_flow/ext/github/hosting.py
proj_flow/ext/github/publishing.py
proj_flow/ext/github/switches.py
proj_flow/ext/python/__init__.py
proj_flow/ext/python/rtdocs.py
proj_flow/ext/python/steps.py
proj_flow/ext/python/version.py
proj_flow/ext/sign/__init__.py
proj_flow/ext/sign/api.py
proj_flow/ext/sign/win32.py
proj_flow/ext/tools/__init__.py
proj_flow/ext/tools/pragma_once.py
proj_flow/ext/tools/run_linter.py
proj_flow/ext/webidl/__init__.py
proj_flow/ext/webidl/registry.py
proj_flow/ext/webidl/base/__init__.py
proj_flow/ext/webidl/base/config.py
proj_flow/ext/webidl/cli/__init__.py
proj_flow/ext/webidl/cli/cmake.py
proj_flow/ext/webidl/cli/depfile.py
proj_flow/ext/webidl/cli/gen.py
proj_flow/ext/webidl/cli/init.py
proj_flow/ext/webidl/cli/root.py
proj_flow/ext/webidl/cli/updater.py
proj_flow/ext/webidl/data/init/flow_webidl.cmake
proj_flow/ext/webidl/data/templates/cmake.mustache
proj_flow-0.20.3.dist-info/METADATA
proj_flow-0.20.3.dist-info/WHEEL
proj_flow-0.20.3.dist-info/entry_points.txt
proj_flow-0.20.3.dist-info/licenses/LICENSE
proj_flow-0.20.3.dist-info/RECORD
