Metadata-Version: 2.4
Name: proj-flow
Version: 0.20.3
Summary: C++ project maintenance, automated
Project-URL: Changelog, https://github.com/mzdun/proj-flow/blob/main/CHANGELOG.rst
Project-URL: Documentation, https://proj-flow.readthedocs.io/en/latest/
Project-URL: Homepage, https://pypi.org/project/proj-flow/
Project-URL: Source Code, https://github.com/mzdun/proj-flow
Author-email: Marcin Zdun <marcin.zdun@gmail.com>
License-File: LICENSE
Keywords: C/C++,build-tool,c++,ci-cd,continuous-integration,cpp,dependencies,dependency-manager,developer,developer-tools,development,meta-build-tool,pipeline,tools-and-automation
Classifier: Development Status :: 4 - Beta
Classifier: Intended Audience :: Developers
Classifier: License :: OSI Approved :: MIT License
Classifier: Operating System :: OS Independent
Classifier: Programming Language :: Python :: 3
Classifier: Programming Language :: Python :: 3.10
Classifier: Topic :: Software Development :: Build Tools
Requires-Python: >=3.10
Requires-Dist: argcomplete
Requires-Dist: chevron2021
Requires-Dist: prompt-toolkit
Requires-Dist: pywebidl2
Requires-Dist: pyyaml
Requires-Dist: requests-cache
Requires-Dist: toml
